MANIFEST.in
requirements.txt
setup.cfg
setup.py
napalm_eos/__init__.py
napalm_eos/eos.py
napalm_eos.egg-info/PKG-INFO
napalm_eos.egg-info/SOURCES.txt
napalm_eos.egg-info/dependency_links.txt
napalm_eos.egg-info/requires.txt
napalm_eos.egg-info/top_level.txt
napalm_eos/templates/delete_ntp_servers.j2
napalm_eos/templates/delete_snmp_config.j2
napalm_eos/templates/delete_users.j2
napalm_eos/templates/set_ntp_servers.j2
napalm_eos/templates/set_users.j2
napalm_eos/templates/snmp_config.j2
napalm_eos/utils/__init__.py
napalm_eos/utils/textfsm_templates/bgp_detail.tpl
napalm_eos/utils/textfsm_templates/ntp_peers.tpl
napalm_eos/utils/textfsm_templates/snmp_config.tpl
napalm_eos/utils/textfsm_templates/vrf.tpl